{
    "Dropbox":  {
                    "Append":  false,
                    "Mirror":  false,
                    "Source":  "D:\\Documents\\GitHub\\portfolio.github.io",
                    "Name":  "portfolio.github.io",
                    "Freq":  "Daily",
                    "Zip":  true,
                    "Keep":  1,
                    "Dest":  "C:\\Users\\Lenovo\\Dropbox"
                },
    "Mega":  {
                 "Append":  false,
                 "Mirror":  true,
                 "Source":  "D:\\Documents\\MegaSync\\NZMA;D:\\Documents\\MegaSync\\Personal",
                 "Name":  "",
                 "Freq":  null,
                 "Zip":  false,
                 "Keep":  2,
                 "Dest":  "D:\\Documents\\Mega"
             },
    "Google":  {
                   "Append":  false,
                   "Mirror":  true,
                   "Source":  "D:\\Documents\\GoogleDriveSync\\Books;D:\\Documents\\GoogleDriveSync\\Piano;D:\\Documents\\GoogleDriveSync\\SketchUp;D:\\Documents\\GoogleDriveSync\\Software;D:\\Documents\\GoogleDriveSync\\Woodwork;D:\\Documents\\GoogleDriveSync\\Zoom",
                   "Name":  "",
                   "Freq":  "Daily",
                   "Zip":  false,
                   "Keep":  3,
                   "Dest":  "D:\\Documents\\Google Drive"
               }
}
